BubbleDet/__init__.py
BubbleDet/configs.py
BubbleDet/derivative_expansion.py
BubbleDet/determinant.py
BubbleDet/extrapolation.py
BubbleDet/gelfand_yaglom.py
BubbleDet/group_volumes.py
BubbleDet/helpers.py
BubbleDet/laplacian.py
BubbleDet/negative_eigenvalue.py
BubbleDet/phi_infinity.py
BubbleDet/renormalisation.py
BubbleDet/wkb.py
BubbleDet-1.0.7.dist-info/LICENSE
BubbleDet-1.0.7.dist-info/METADATA
BubbleDet-1.0.7.dist-info/WHEEL
BubbleDet-1.0.7.dist-info/top_level.txt
BubbleDet-1.0.7.dist-info/RECORD
