Metadata-Version: 2.1
Name: BubbleDet
Version: 1.0.7
Summary: A package for computing functional determinants
Author-email: Andreas Ekstedt <andreas.ekstedt@desy.de>, Oliver Gould <oliver.gould@nottingham.ac.uk>, Joonas Hirvonen <joonas.o.hirvonen@helsinki.fi>
License: MIT
Project-URL: Homepage, https://bubbledet.readthedocs.io/
Project-URL: Repository, https://bitbucket.org/og113/bubbledet/
Classifier: Topic :: Scientific/Engineering :: Physics
Requires-Python: >=3.7
License-File: LICENSE
Requires-Dist: cosmoTransitions >=2.0.6
Requires-Dist: findiff >=0.9.2
Requires-Dist: numpy >=1.21.5
Requires-Dist: packaging >=21.3
Requires-Dist: scipy >=1.8.0
Provides-Extra: docs
Requires-Dist: graphviz ; extra == 'docs'
Requires-Dist: sphinx ; extra == 'docs'
Requires-Dist: sphinx-rtd-theme ; extra == 'docs'
Requires-Dist: sphinx-automodapi ; extra == 'docs'
Requires-Dist: sphinxcontrib-bibtex ; extra == 'docs'
Provides-Extra: tests
Requires-Dist: pytest >=7.2.2 ; extra == 'tests'
Requires-Dist: matplotlib >=3.5.1 ; extra == 'tests'
